<?xml version='1.0' encoding='UTF-8' standalone='yes' ?>
<hierarchy index="0" class="hierarchy" rotation="0" width="768" height="1184">
  <android.widget.FrameLayout index="0" package="bbc.mobile.news.uk" class="android.widget.FrameLayout" text="" checkable="false" checked="false" clickable="false" enabled="true" focusable="false" focused="false" long-clickable="false" password="false" scrollable="false" selected="false" bounds="[19,203][748,1029]" displayed="true">
    <android.widget.FrameLayout index="0" package="bbc.mobile.news.uk" class="android.widget.FrameLayout" text="" checkable="false" checked="false" clickable="false" enabled="true" focusable="false" focused="false" long-clickable="false" password="false" scrollable="false" selected="false" bounds="[51,235][716,997]" displayed="true">
      <android.widget.FrameLayout index="0" package="bbc.mobile.news.uk" class="android.widget.FrameLayout" text="" resource-id="android:id/content" checkable="false" checked="false" clickable="false" enabled="true" focusable="false" focused="false" long-clickable="false" password="false" scrollable="false" selected="false" bounds="[51,235][716,997]" displayed="true">
        <android.widget.LinearLayout index="0" package="bbc.mobile.news.uk" class="android.widget.LinearLayout" text="" resource-id="android:id/parentPanel" checkable="false" checked="false" clickable="false" enabled="true" focusable="false" focused="false" long-clickable="false" password="false" scrollable="false" selected="false" bounds="[51,235][716,997]" displayed="true">
          <android.widget.LinearLayout index="0" package="bbc.mobile.news.uk" class="android.widget.LinearLayout" text="" resource-id="android:id/topPanel" checkable="false" checked="false" clickable="false" enabled="true" focusable="false" focused="false" long-clickable="false" password="false" scrollable="false" selected="false" bounds="[51,235][716,341]" displayed="true">
            <android.widget.LinearLayout index="0" package="bbc.mobile.news.uk" class="android.widget.LinearLayout" text="" resource-id="android:id/title_template" checkable="false" checked="false" clickable="false" enabled="true" focusable="false" focused="false" long-clickable="false" password="false" scrollable="false" selected="false" bounds="[51,235][716,325]" displayed="true">
              <android.widget.TextView index="0" package="bbc.mobile.news.uk" class="android.widget.TextView" text="Share" resource-id="android:id/alertTitle" checkable="false" checked="false" clickable="false" enabled="true" focusable="false" focused="false" long-clickable="false" password="false" scrollable="false" selected="false" bounds="[99,271][668,325]" displayed="true" />
            </android.widget.LinearLayout>
            <android.view.View index="1" package="bbc.mobile.news.uk" class="android.view.View" text="" resource-id="android:id/titleDividerNoCustom" checkable="false" checked="false" clickable="false" enabled="true" focusable="false" focused="false" long-clickable="false" password="false" scrollable="false" selected="false" bounds="[51,325][716,341]" displayed="true" />
          </android.widget.LinearLayout>
          <android.widget.FrameLayout index="1" package="bbc.mobile.news.uk" class="android.widget.FrameLayout" text="" resource-id="android:id/contentPanel" checkable="false" checked="false" clickable="false" enabled="true" focusable="false" focused="false" long-clickable="false" password="false" scrollable="false" selected="false" bounds="[51,341][716,997]" displayed="true">
            <android.widget.ListView index="0" package="bbc.mobile.news.uk" class="android.widget.ListView" text="" resource-id="android:id/select_dialog_listview" checkable="false" checked="false" clickable="false" enabled="true" focusable="true" focused="true" long-clickable="false" password="false" scrollable="false" selected="false" bounds="[51,341][716,997]" displayed="true">
              <android.widget.TextView index="0" package="bbc.mobile.news.uk" class="android.widget.TextView" text="Bluetooth" resource-id="android:id/text1" checkable="false" checked="false" clickable="true" enabled="true" focusable="false" focused="false" long-clickable="false" password="false" scrollable="false" selected="false" bounds="[51,341][716,469]" displayed="true" />
              <android.widget.TextView index="1" package="bbc.mobile.news.uk" class="android.widget.TextView" text="Save to Drive" resource-id="android:id/text1" checkable="false" checked="false" clickable="true" enabled="true" focusable="false" focused="false" long-clickable="false" password="false" scrollable="false" selected="false" bounds="[51,469][716,597]" displayed="true" />
              <android.widget.TextView index="2" package="bbc.mobile.news.uk" class="android.widget.TextView" text="Messages" resource-id="android:id/text1" checkable="false" checked="false" clickable="true" enabled="true" focusable="false" focused="false" long-clickable="false" password="false" scrollable="false" selected="false" bounds="[51,597][716,725]" displayed="true" />
              <android.widget.TextView index="3" package="bbc.mobile.news.uk" class="android.widget.TextView" text="Gmail" resource-id="android:id/text1" checkable="false" checked="false" clickable="true" enabled="true" focusable="false" focused="false" long-clickable="false" password="false" scrollable="false" selected="false" bounds="[51,725][716,853]" displayed="true" />
              <android.widget.TextView index="4" package="bbc.mobile.news.uk" class="android.widget.TextView" text="Notepad Free" resource-id="android:id/text1" checkable="false" checked="false" clickable="true" enabled="true" focusable="false" focused="false" long-clickable="false" password="false" scrollable="false" selected="false" bounds="[51,853][716,981]" displayed="true" />
            </android.widget.ListView>
          </android.widget.FrameLayout>
        </android.widget.LinearLayout>
      </android.widget.FrameLayout>
    </android.widget.FrameLayout>
  </android.widget.FrameLayout>
</hierarchy>